MANIFEST.in
charmed_traceback/__init__.py
charmed_traceback/__main__.py
charmed_traceback/always/__init__.py
charmed_traceback/auto/__init__.py
charmed_traceback/charmed_traceback.py
charmed_traceback/py.typed
charmed_traceback-0.1.2.dist-info/WHEEL
charmed_traceback-0.1.2.dist-info/METADATA
charmed_traceback-0.1.2.dist-info/RECORD
