Metadata-Version: 2.1
Name: charmed-traceback
Version: 0.1.2
Summary: Automatically apply traceback styling akin to Jetbrains Traceback highlighting, providing much easier debugging and log searching, as-well as feel more at home away from PyCharm
Home-page: https://github.com/Gideon-Felt/charmed_traceback
License: MIT
Keywords: traceback,styling,developer
Author: Gideon Felt
Author-email: gideonfelt.dev@gmail.com
Requires-Python: >=3.7.0,<4.0
Classifier: Development Status :: 4 - Beta
Classifier: Environment :: Console
Classifier: Intended Audience :: Developers
Classifier: License :: OSI Approved :: MIT License
Classifier: Natural Language :: English
Classifier: Operating System :: MacOS :: MacOS X
Classifier: Operating System :: Microsoft :: Windows
Classifier: Operating System :: POSIX :: Linux
Classifier: Programming Language :: Python
Classifier: Programming Language :: Python :: 3
Classifier: Programming Language :: Python :: 3.10
Classifier: Programming Language :: Python :: 3.7
Classifier: Programming Language :: Python :: 3.8
Classifier: Programming Language :: Python :: 3.9
Project-URL: Repository, https://github.com/Gideon-Felt/charmed_traceback
